{
  "todos": [
    {
      "userId": 1,
      "id": "1",
      "title": "Buy groceries",
      "completed": false
    },
    {
      "userId": 1,
      "id": "2",
      "title": "Finish report",
      "completed": false
    },
    {
      "userId": 1,
      "id": "3",
      "title": "Clean the house",
      "completed": false
    },
    {
      "userId": 1,
      "id": "4",
      "title": "Go for a walk",
      "completed": false
    },
    {
      "userId": 1,
      "id": "5",
      "title": "Make a dentist appointment",
      "completed": false
    },
    {
      "userId": 1,
      "id": "6",
      "title": "Water the plants",
      "completed": false
    },
    {
      "userId": 1,
      "id": "7",
      "title": "Call mom",
      "completed": false
    },
    {
      "id": "300",
      "userId": 400,
      "title": "Buy Toys",
      "completed": false
    }
  ]
}